{"id":2398100,"titles":{"en":"Damion#Damion#Damion"},"slug":"Damion","sale_mode":0,"type":35,"element_sub_type":0,"is_custom":0,"last_modified":"2022-12-15T02:07:46-08:00","description":"","thumbnail_url":"https://static-eus-rs.wondershare.com/Filmora_Win/file/s6/befa6d1fc27f994c4862517712865948.png","preview_url":"","frame_url":"","recent_use_time":0,"third_required_info":0,"timeline_data_info":"","background_urls":[],"related_id":2047068,"need_update":false,"secret_key":"V4#@c84dc2335fe621951af3a7a3a077bf1607025dd4752d35bbd76375e70b3e1c955c9ebdfec798338436a73e5edf00ba60","related_type":2,"version":"1.0.1","related_info":{"id":2047068,"slug":"","title":{"Damion":"zh-cn"}},"extension":{"split_thumbs":{},"split_previews":{},"template_base":{"third_url":"","duration":"","frame":"","ratio":"","is_recommend":0},"openFx_extension":{"element_sub_type":0},"audio_info":{"audition_music":"","singer":"","duration":0,"waveform_data":"[]"}},"download_from":{"category_id":0,"category_slug":"","download_author":"","download_lang":"","download_time":0,"category_titles":{}},"categories":[{"id":97202,"name":"All Fonts","slug":"font_allfonts_en"},{"id":109036,"name":"Damion","slug":"font_Damion_en"}],"attributes":[],"tags":[],"labels":[],"diskInfo":{"id":0,"file_id":"","thumb_id":"","size":0,"create_time":0,"update_time":0,"version":""},"download_Info":{
    "id": 2398100,
    "name": "Damion",
    "res_type": 35,
    "sale_mode": 0,
    "is_custom": 0,
    "infoType": 7,
    "resource_rate": 4
}}