{"id":2398224,"titles":{"en":"Raleway ExtraLightItalic#Raleway ExtraLight Italic#Raleway"},"slug":"Raleway_ExtraLight_Italic","sale_mode":0,"type":35,"element_sub_type":0,"is_custom":0,"last_modified":"2022-12-15T01:43:45-08:00","description":"","thumbnail_url":"https://static-eus-rs.wondershare.com/Filmora_Win/file/s1/35c9a6920fbc19e68783c506d6279163.png","preview_url":"","frame_url":"","recent_use_time":0,"third_required_info":0,"timeline_data_info":"","background_urls":[],"related_id":2047192,"need_update":false,"secret_key":"V4#@c02fca24473010a81b520e7e795820db4389680a07008d1097cb1fa24f2d83e3319f21fe13bc39447d04e67487842a71334039cb17624bc9501970354c8df82e","related_type":2,"version":"1.0.2","related_info":{"id":2047192,"slug":"","title":{"Raleway ExtraLight Italic":"zh-cn"}},"extension":{"split_thumbs":{},"split_previews":{},"template_base":{"third_url":"","duration":"","frame":"","ratio":"","is_recommend":0},"openFx_extension":{"element_sub_type":0},"audio_info":{"audition_music":"","singer":"","duration":0,"waveform_data":"[]"}},"download_from":{"category_id":0,"category_slug":"","download_author":"","download_lang":"","download_time":0,"category_titles":{}},"categories":[{"id":97202,"name":"All Fonts","slug":"font_allfonts_en"},{"id":117080,"name":"Raleway","slug":"font_Raleway_en"}],"attributes":[],"tags":[],"labels":[],"diskInfo":{"id":0,"file_id":"","thumb_id":"","size":0,"create_time":0,"update_time":0,"version":""},"download_Info":{
    "id": 2398224,
    "name": "Raleway_ExtraLight_Italic",
    "res_type": 35,
    "sale_mode": 0,
    "is_custom": 0,
    "infoType": 7,
    "resource_rate": 4
}}